{
	"type" : "FeatureCollection",
	"name" : "Output",
	"features" : [
		{
			"type" : "Feature",
			"geometry" : {
				"type" : "Point",
				"coordinates" : [ 4.8239553403, 43.9271979251 ]
			},
			"properties" : {
				"name" : "16 : Visite Bibliothèque éphémère",
				"description" : "Mise en avant du mode constructif de la bibliothèque basé sur des containers maritimes recyclés permettant un démontage « facile » pour être implantés sur autre site tout en proposant un confort d’usage élevé\n** Conditions d'accès :**\nmardi 28 septembre, 17h00\n**Adresse : **\nParc du Clos de la Murette\n"
			}
		}
	]
}