{
	"type" : "FeatureCollection",
	"name" : "Output",
	"features" : [
		{
			"type" : "Feature",
			"geometry" : {
				"type" : "Point",
				"coordinates" : [ 4.808754544, 43.9515019225 ]
			},
			"properties" : {
				"name" : "7 : Manutention",
				"description" : "Du 8 au 25 septembre 2022 : SOCIETE FRANÇAISE DE L’AQUARELLE « Ponts et déchirures »\nL'aquarelle est une écriture \"d'eau et d'âme\", une écriture de la trace, de l'évocation, et si l'on y associe d'autres écritures : celle des mots avec la poésie de René Char, des graphismes avec la calligraphie, et celle en devenir des jeunes de nos écoles, nous avançons dans une ECRITURE SENSIBLE, un support relationnel, lien, un pont universel pour dépasser nos déchirures …et entrer en résilience. Ainsi, notre rôle d’artistes contemporains, nous conduira lors de cette exposition au Cloître St Louis à développer cette recherche à travers la réunion des œuvres de nos meilleurs artistes aquarellistes français, témoins et acteurs de notre actualité, dans la grande diversité de leurs écritures.   Par ailleurs, la ville d’Avignon par la symbolique de ses ponts, nous a amené à rechercher des liens locaux, des ponts que nous allons créer et développer avec les acteurs du passé et du présent avignonnais : l’œuvre du poète René Char, les enfants de la classe de CM avec leur institutrice Maud Bertrand de l'école St Roch d'Avignon qui exposeront à nos côtés ainsi que la prestation d'une artiste calligraphe avignonnaise.  Un calendrier de rencontres avec le public sera établi. \n** Conditions d'accès :**\nTous les jours de 14h à 18h30, sauf les lundis \n* **Gratuit** *\n**Adresse : **\n4, rue des Escaliers Sainte-Anne            84000 AVIGNON\n"
			}
		},
		{
			"type" : "Feature",
			"geometry" : {
				"type" : "Point",
				"coordinates" : [ 4.8057902952, 43.9445336006 ]
			},
			"properties" : {
				"name" : "8 : Exposition « Trois héritages d’exception »",
				"description" : "La ville d’Avignon a reçu consécutivement entre 2016 et 2018 trois legs ou donations de la part de trois femmes : Elizabeth Pommer, Michèle Azémar et Françoise Taillandier. Les Bains Pommer et l’Hôtel de Beaumont sont classés partiellement ou en totalité monuments historiques tandis que les œuvres de Yvon Taillandier offrent une collection protéiforme et unique. Les Bains Pommer et l’Hôtel de Beaumont sont en cours de restauration pour devenir à terme des lieux de découverte culturelle.\n* **Gratuit** *\n**Adresse : **\nSquare Agricol Perdiguier                  Cours Jean Jaures 84000 AVIGNON\n"
			}
		},
		{
			"type" : "Feature",
			"geometry" : {
				"type" : "Point",
				"coordinates" : [ 4.8045764051, 43.9436863385 ]
			},
			"properties" : {
				"name" : "6 : Cloître Saint-Louis",
				"description" : "Du 8 au 25 septembre 2022 : SOCIETE FRANÇAISE DE L’AQUARELLE « Ponts et déchirures »\nL'aquarelle est une écriture \"d'eau et d'âme\", une écriture de la trace, de l'évocation, et si l'on y associe d'autres écritures : celle des mots avec la poésie de René Char, des graphismes avec la calligraphie, et celle en devenir des jeunes de nos écoles, nous avançons dans une ECRITURE SENSIBLE, un support relationnel, lien, un pont universel pour dépasser nos déchirures …et entrer en résilience. Ainsi, notre rôle d’artistes contemporains, nous conduira lors de cette exposition au Cloître St Louis à développer cette recherche à travers la réunion des œuvres de nos meilleurs artistes aquarellistes français, témoins et acteurs de notre actualité, dans la grande diversité de leurs écritures.   Par ailleurs, la ville d’Avignon par la symbolique de ses ponts, nous a amené à rechercher des liens locaux, des ponts que nous allons créer et développer avec les acteurs du passé et du présent avignonnais : l’œuvre du poète René Char, les enfants de la classe de CM avec leur institutrice Maud Bertrand de l'école St Roch d'Avignon qui exposeront à nos côtés ainsi que la prestation d'une artiste calligraphe avignonnaise.  Un calendrier de rencontres avec le public sera établi. \n** Conditions d'accès :**\nTous les jours de 14h à 18h30, sauf les lundis \n* **Gratuit** *\n**Adresse : **\n20 rue du Portail Boquier                       84000 AVIGNON\n"
			}
		}
	]
}